water_properties/__init__.py
water_properties/water_prop.py
water_property-1.0.0.dist-info/licenses/LICENSE.txt
water_property-1.0.0.dist-info/METADATA
water_property-1.0.0.dist-info/WHEEL
water_property-1.0.0.dist-info/top_level.txt
water_property-1.0.0.dist-info/RECORD
