Metadata-Version: 2.4
Name: water_property
Version: 1.0.0
Summary: A module to get water properties from a temperature dataset
Author: Nilesh Mishra
Author-email: nkm.full.stack@gmail.com
Classifier: Programming Language :: Python :: 3
Classifier: License :: OSI Approved :: MIT License
Classifier: Operating System :: OS Independent
Classifier: Intended Audience :: Developers
Classifier: Topic :: Scientific/Engineering
Requires-Python: >=3.6
License-File: LICENSE.txt
Requires-Dist: numpy
Requires-Dist: pandas
Dynamic: license-file
